aigrok/__init__.py
aigrok/api.py
aigrok/cli.py
aigrok/config.py
aigrok/formats.py
aigrok/logging.py
aigrok/pdf_processor.py
aigrok/types.py
aigrok/validation.py
aigrok-0.3.3.dist-info/LICENSE
aigrok-0.3.3.dist-info/METADATA
aigrok-0.3.3.dist-info/WHEEL
aigrok-0.3.3.dist-info/entry_points.txt
aigrok-0.3.3.dist-info/top_level.txt
aigrok-0.3.3.dist-info/RECORD
