Metadata-Version: 2.1
Name: aigrok
Version: 0.3.3
Summary: A Python package for document processing and analysis with LLM integration and OCR capabilities
Author-email: aigrok <brooksc@brooksc.com>
Project-URL: Homepage, https://github.com/brooksc/aigrok
Project-URL: Repository, https://github.com/brooksc/aigrok.git
Classifier: Development Status :: 3 - Alpha
Classifier: Intended Audience :: Developers
Classifier: License :: OSI Approved :: MIT License
Classifier: Operating System :: OS Independent
Classifier: Programming Language :: Python :: 3
Classifier: Programming Language :: Python :: 3.8
Classifier: Programming Language :: Python :: 3.9
Classifier: Programming Language :: Python :: 3.10
Classifier: Programming Language :: Python :: 3.11
Classifier: Programming Language :: Python :: 3.12
Requires-Python: >=3.8
License-File: LICENSE
Requires-Dist: pypdf>=5.1.0
Requires-Dist: python-dotenv>=1.0.0
Requires-Dist: pytest>=7.4.3
Requires-Dist: pytest-cov>=4.1.0
Requires-Dist: pydantic>=2.5.2
Requires-Dist: loguru>=0.7.2
Requires-Dist: requests>=2.31.0
Requires-Dist: pillow>=10.1.0
Requires-Dist: ollama>=0.1.6
Requires-Dist: litellm>=1.30.3
Requires-Dist: pymupdf>=1.23.8
Requires-Dist: pyyaml>=6.0.1
Requires-Dist: easyocr>=1.7.1
